lab4/c/src/dff.vhd
library ieee;
use ieee.std_logic_1164.all;
entity dff is 
  port ( 
    -- System Clock and Reset
    rst_n     : in  std_logic;   -- Reset
    mclk      : in  std_logic;   -- Clock
    -- Shifted data in and out
    din       : in  std_logic;   -- Data in
    dout      : out std_logic    -- Data out
  );      
end dff;
architecture rtl of dff is 
begin
  P_DFF : process(rst_n, mclk)
  begin
    if rst_n='0' then
      dout <= '0';
    elsif rising_edge(mclk) then
      dout <= din;
    end if;
  end process P_DFF;  
end rtl;

-- This is a D- flipflop (dff)! :D

lab4/b/src/shift8.vhd
library ieee;
use ieee.std_logic_1164.all;

entity shift8 is

  port(
      rst_n : in std_logic;
      mclk : in std_logic;
      in_ser : in std_logic;
      out_ser : out std_logic;
      out_par : out std_logic_vector(7 downto 0)
  );

end shift8;

architecture shift_arc of shift8 is

  signal shift_register : std_logic_vector(8 downto 0);
  
  component dff is -- ikke endre denne! Den skal være lik som entitet i dff.vhd
    port(
        rst_n     : in  std_logic;   -- Reset
        mclk      : in  std_logic;   -- Clock
        -- Shifted data in and out
        din       : in  std_logic;   -- Data in
        dout      : out std_logic    -- Data out
        );
  end component;
  begin
    instantiating_loop : for i in 0 to 7 generate komponent: dff
      port map(
              --din => din(i)
              --dout => dout(i)
              rst_n => rst_n, --good
              mclk => mclk, --good
              dout => shift_register(i+1),
              din => shift_register(i)
              );
    end generate;

  shift_register(0) <= in_ser;
  out_par <= shift_register(8 downto 1);
  out_ser <= shift_register(8);

end shift_arc;

lab4/b/src/tb_shift8.vhd
library ieee;
use ieee.std_logic_1164.all;

entity tb_shift8 is
  -- empty;
end tb_shift8;

architecture behavioural of tb_shift8 is
  
  -- see https://vhdlwhiz.com/clocked-process/
  constant clk_freq : integer := 2; 
  constant clk_period : time := 100 ns / clk_freq;

  signal mclk : std_logic := '1';
  signal rst_n : std_logic := '0';
  signal in_ser : std_logic := '0';
  signal out_ser : std_logic;
  signal out_par : std_logic_vector(7 downto 0);


  component shift8
    port(
        rst_n : in std_logic;
        mclk : in std_logic;
        in_ser : in std_logic;
        out_ser : out std_logic;
        out_par : out std_logic_vector(7 downto 0)
      );
  end component;

begin

  UUT_0: entity work.shift8(shift_arc) -- ikke endre denne! Den skal være lik som entitet i dff.vhd
    port map(
            rst_n  => rst_n,
            mclk => mclk,
            in_ser => in_ser,
            out_ser => out_ser,
            out_par => out_par
            );

  mclk <= not mclk after clk_period/2; -- process that generates clock

  process is
  begin
    rst_n <= '1';
    wait for 50 ns;
    in_ser <= '1';
    wait for 50 ns;
    in_ser <= '0';
    wait for 50 ns;
    in_ser <= '0';
    wait for 50 ns;
    in_ser <= '0';
    wait for 50 ns;
    in_ser <= '1';
    wait;
    end process;
end behavioural;

lab4/c/src/wave.vcd
$date
  Tue Feb 14 18:11:40 2023
$end
$version
  GHDL v0
$end
$timescale
  1 fs
$end
$scope module standard $end
$upscope $end
$scope module textio $end
$upscope $end
$scope module std_logic_1164 $end
$upscope $end
$scope module tb_shift8 $end
$var reg 1 ! mclk $end
$var reg 1 " rst_n $end
$var reg 1 # in_ser $end
$var reg 1 $ out_ser $end
$var reg 8 % out_par[7:0] $end
$scope module uut_0 $end
$var reg 1 & rst_n $end
$var reg 1 ' mclk $end
$var reg 1 ( in_ser $end
$var reg 1 ) out_ser $end
$var reg 8 * out_par[7:0] $end
$var reg 9 + shift_register[8:0] $end
$scope module instantiating_loop(0) $end
$scope module komponent $end
$var reg 1 , rst_n $end
$var reg 1 - mclk $end
$var reg 1 . din $end
$var reg 1 / dout $end
$upscope $end
$upscope $end
$scope module instantiating_loop(1) $end
$scope module komponent $end
$var reg 1 0 rst_n $end
$var reg 1 1 mclk $end
$var reg 1 2 din $end
$var reg 1 3 dout $end
$upscope $end
$upscope $end
$scope module instantiating_loop(2) $end
$scope module komponent $end
$var reg 1 4 rst_n $end
$var reg 1 5 mclk $end
$var reg 1 6 din $end
$var reg 1 7 dout $end
$upscope $end
$upscope $end
$scope module instantiating_loop(3) $end
$scope module komponent $end
$var reg 1 8 rst_n $end
$var reg 1 9 mclk $end
$var reg 1 : din $end
$var reg 1 ; dout $end
$upscope $end
$upscope $end
$scope module instantiating_loop(4) $end
$scope module komponent $end
$var reg 1 < rst_n $end
$var reg 1 = mclk $end
$var reg 1 > din $end
$var reg 1 ? dout $end
$upscope $end
$upscope $end
$scope module instantiating_loop(5) $end
$scope module komponent $end
$var reg 1 @ rst_n $end
$var reg 1 A mclk $end
$var reg 1 B din $end
$var reg 1 C dout $end
$upscope $end
$upscope $end
$scope module instantiating_loop(6) $end
$scope module komponent $end
$var reg 1 D rst_n $end
$var reg 1 E mclk $end
$var reg 1 F din $end
$var reg 1 G dout $end
$upscope $end
$upscope $end
$scope module instantiating_loop(7) $end
$scope module komponent $end
$var reg 1 H rst_n $end
$var reg 1 I mclk $end
$var reg 1 J din $end
$var reg 1 K dout $end
$upscope $end
$upscope $end
$upscope $end
$upscope $end
$enddefinitions $end
#0
1!
1"
0#
0$
b00000000 %
1&
1'
0(
0)
b00000000 *
b000000000 +
1,
1-
0.
0/
10
11
02
03
14
15
06
07
18
19
0:
0;
1<
1=
0>
0?
1@
1A
0B
0C
1D
1E
0F
0G
1H
1I
0J
0K
#25000000
0!
0'
0-
01
05
09
0=
0A
0E
0I
#50000000
1!
1#
1'
1(
b000000001 +
1-
1.
11
15
19
1=
1A
1E
1I
#75000000
0!
0'
0-
01
05
09
0=
0A
0E
0I
#100000000
1!
0#
b00000001 %
1'
0(
b00000001 *
b000000010 +
1-
0.
1/
11
12
15
19
1=
1A
1E
1I
#125000000
0!
0'
0-
01
05
09
0=
0A
0E
0I
#150000000
1!
b00000010 %
1'
b00000010 *
b000000100 +
1-
0/
11
02
13
15
16
19
1=
1A
1E
1I
#175000000
0!
0'
0-
01
05
09
0=
0A
0E
0I
#200000000
1!
b00000100 %
1'
b00000100 *
b000001000 +
1-
11
03
15
06
17
19
1:
1=
1A
1E
1I
#225000000
0!
0'
0-
01
05
09
0=
0A
0E
0I
#250000000
1!
1#
b00001000 %
1'
1(
b00001000 *
b000010001 +
1-
1.
11
15
07
19
0:
1;
1=
1>
1A
1E
1I
#275000000
0!
0'
0-
01
05
09
0=
0A
0E
0I
#300000000
1!
b00010001 %
1'
b00010001 *
b000100011 +
1-
1/
11
12
15
19
0;
1=
0>
1?
1A
1B
1E
1I
#325000000
0!
0'
0-
01
05
09
0=
0A
0E
0I
#350000000
1!
b00100011 %
1'
b00100011 *
b001000111 +
1-
11
13
15
16
19
1=
0?
1A
0B
1C
1E
1F
1I
#375000000
0!
0'
0-
01
05
09
0=
0A
0E
0I
#400000000
1!
b01000111 %
1'
b01000111 *
b010001111 +
1-
11
15
17
19
1:
1=
1A
0C
1E
0F
1G
1I
1J
#425000000
0!
0'
0-
01
05
09
0=
0A
0E
0I
#450000000
1!
1$
b10001111 %
1'
1)
b10001111 *
b100011111 +
1-
11
15
19
1;
1=
1>
1A
1E
0G
1I
0J
1K
#475000000
0!
0'
0-
01
05
09
0=
0A
0E
0I
#500000000
1!
0$
b00011111 %
1'
0)
b00011111 *
b000111111 +
1-
11
15
19
1=
1?
1A
1B
1E
1I
0K
#525000000
0!
0'
0-
01
05
09
0=
0A
0E
0I
#550000000
1!
b00111111 %
1'
b00111111 *
b001111111 +
1-
11
15
19
1=
1A
1C
1E
1F
1I
#575000000
0!
0'
0-
01
05
09
0=
0A
0E
0I
#600000000
1!
b01111111 %
1'
b01111111 *
b011111111 +
1-
11
15
19
1=
1A
1E
1G
1I
1J
#625000000
0!
0'
0-
01
05
09
0=
0A
0E
0I
#650000000
1!
1$
b11111111 %
1'
1)
b11111111 *
b111111111 +
1-
11
15
19
1=
1A
1E
1I
1K
